amunpy/__init__.py
amunpy/amun.py
amunpy/amunh5.py
amunpy/amunh5_deprecated.py
amunpy/amunxml.py
amunpy/integrals.py
amunpy/interpolation.py
amunpy/octree.py
amunpy/vtkio.py
amunpy-0.9.11.dist-info/LICENSE
amunpy-0.9.11.dist-info/METADATA
amunpy-0.9.11.dist-info/WHEEL
amunpy-0.9.11.dist-info/top_level.txt
amunpy-0.9.11.dist-info/RECORD
