Metadata-Version: 2.1
Name: amunpy
Version: 0.9.11
Summary: Python Interface for the AMUN code's snapshots
Home-page: https://www.amuncode.org/
Author: Grzegorz Kowal
Author-email: grzegorz@amuncode.org
Project-URL: Bug Tracker, https://bitbucket.org/amunteam/amun-code/issues
Classifier: Programming Language :: Python :: 3
Classifier: License :: OSI Approved :: GNU General Public License v3 (GPLv3)
Classifier: Operating System :: OS Independent
Requires-Python: >=3.6
License-File: LICENSE
Requires-Dist: h5py
Requires-Dist: numpy
Requires-Dist: xxhash
Requires-Dist: lz4
Requires-Dist: zstandard
Provides-Extra: interpolation
Requires-Dist: scipy ; extra == 'interpolation'
